{"v":"5.6.6","fr":24,"ip":0,"op":66,"w":1920,"h":1920,"nm":"12","ddd":0,"assets":[],"layers":[{"ddd":0,"ind":1,"ty":4,"nm":"hair Outlines","sr":1,"ks":{"o":{"a":0,"k":100,"ix":11},"r":{"a":0,"k":0,"ix":10},"p":{"a":1,"k":[{"i":{"x":0.462,"y":1},"o":{"x":0.67,"y":0.011},"t":0,"s":[991.919,934.786,0],"to":[0,6.667,0],"ti":[0,3.333,0]},{"i":{"x":0.328,"y":1},"o":{"x":0.632,"y":0.004},"t":20,"s":[991.919,974.786,0],"to":[0,-3.333,0],"ti":[0,6.667,0]},{"i":{"x":0.176,"y":1},"o":{"x":0.333,"y":0},"t":31,"s":[991.919,914.786,0],"to":[0,-6.667,0],"ti":[0,-3.333,0]},{"t":65,"s":[991.919,934.786,0]}],"ix":2},"a":{"a":0,"k":[319.368,161.531,0],"ix":1},"s":{"a":0,"k":[100,100,100],"ix":6}},"ao":0,"shapes":[{"ty":"gr","it":[{"ind":0,"ty":"sh","ix":1,"ks":{"a":1,"k":[{"i":{"x":0.667,"y":1},"o":{"x":0.333,"y":0},"t":0,"s":[{"i":[[-41.994,-57.179],[0,0],[-17.166,25.748],[0,-14.305],[-31.47,-60.079],[203.144,0.377]],"o":[[51.497,-51.496],[0,0],[17.165,62.94],[0,14.305],[60.079,31.471],[-271.808,-0.505]],"v":[[-255.925,138.393],[-81.409,92.619],[-41.357,-76.175],[-7.026,86.897],[259.04,129.81],[25.888,-154.281]],"c":true}]},{"i":{"x":0.667,"y":1},"o":{"x":0.333,"y":0},"t":20,"s":[{"i":[[16.006,-65.179],[0,0],[-17.166,25.748],[0,-14.305],[-31.47,-60.079],[203.144,0.377]],"o":[[51.497,-51.496],[0,0],[17.165,62.94],[0,14.305],[60.079,31.471],[-271.808,-0.505]],"v":[[-255.925,138.393],[-81.409,92.619],[-41.356,-76.175],[-7.026,86.897],[259.04,129.81],[23.888,-196.281]],"c":true}]},{"i":{"x":0.667,"y":1},"o":{"x":0.333,"y":0},"t":31,"s":[{"i":[[16.006,-65.179],[0,0],[-17.166,25.748],[0,-14.305],[-31.47,-60.079],[203.144,0.377]],"o":[[51.497,-51.496],[0,0],[17.165,62.94],[0,14.305],[60.079,31.471],[-271.808,-0.505]],"v":[[-255.925,138.393],[-81.409,92.619],[-41.356,-44.175],[-7.026,86.897],[259.04,129.81],[23.888,-136.281]],"c":true}]},{"t":65,"s":[{"i":[[-41.994,-57.179],[0,0],[-17.166,25.748],[0,-14.305],[-31.47,-60.079],[203.144,0.377]],"o":[[51.497,-51.496],[0,0],[17.165,62.94],[0,14.305],[60.079,31.471],[-271.808,-0.505]],"v":[[-255.925,138.393],[-81.409,92.619],[-41.357,-76.175],[-7.026,86.897],[259.04,129.81],[25.888,-154.281]],"c":true}]}],"ix":2},"nm":"Path 1","mn":"ADBE Vector Shape - Group","hd":false},{"ty":"mm","mm":4,"nm":"Merge Paths 1","mn":"ADBE Vector Filter - Merge","hd":false},{"ty":"fl","c":{"a":0,"k":[0.941176530427,0.549019607843,0.129411764706,1],"ix":4},"o":{"a":0,"k":100,"ix":5},"r":1,"bm":0,"nm":"Fill 1","mn":"ADBE Vector Graphic - Fill","hd":false},{"ty":"tr","p":{"a":0,"k":[319.368,161.531],"ix":2},"a":{"a":0,"k":[0,0],"ix":1},"s":{"a":0,"k":[100,100],"ix":3},"r":{"a":0,"k":0,"ix":6},"o":{"a":0,"k":100,"ix":7},"sk":{"a":0,"k":0,"ix":4},"sa":{"a":0,"k":0,"ix":5},"nm":"Transform"}],"nm":"Group 1","np":3,"cix":2,"bm":0,"ix":1,"mn":"ADBE Vector Group","hd":false}],"ip":0,"op":514,"st":0,"bm":0},{"ddd":0,"ind":2,"ty":4,"nm":"eye b Outlines","parent":6,"sr":1,"ks":{"o":{"a":0,"k":100,"ix":11},"r":{"a":0,"k":0,"ix":10},"p":{"a":1,"k":[{"i":{"x":0.667,"y":1},"o":{"x":0.333,"y":0},"t":29,"s":[179.786,-97.29,0],"to":[0,0,0],"ti":[0,0,0]},{"i":{"x":0.667,"y":1},"o":{"x":0.333,"y":0},"t":51.154,"s":[179.786,-121.29,0],"to":[0,0,0],"ti":[0,0,0]},{"t":65,"s":[179.786,-97.29,0]}],"ix":2},"a":{"a":0,"k":[277.728,31.292,0],"ix":1},"s":{"a":0,"k":[100,100,100],"ix":6}},"ao":0,"shapes":[{"ty":"gr","it":[{"ind":0,"ty":"sh","ix":1,"ks":{"a":0,"k":{"i":[[6.963,-47.533],[64.061,-20.371],[-40.386,0]],"o":[[0,0],[-64.061,20.371],[40.386,0]],"v":[[94.699,16.491],[-37.601,10.671],[0,-27.161]],"c":true},"ix":2},"nm":"Path 1","mn":"ADBE Vector Shape - Group","hd":false},{"ty":"fl","c":{"a":0,"k":[0.941176530427,0.549019607843,0.129411764706,1],"ix":4},"o":{"a":0,"k":100,"ix":5},"r":1,"bm":0,"nm":"Fill 1","mn":"ADBE Vector Graphic - Fill","hd":false},{"ty":"tr","p":{"a":0,"k":[101.912,31.292],"ix":2},"a":{"a":0,"k":[0,0],"ix":1},"s":{"a":0,"k":[100,100],"ix":3},"r":{"a":0,"k":0,"ix":6},"o":{"a":0,"k":100,"ix":7},"sk":{"a":0,"k":0,"ix":4},"sa":{"a":0,"k":0,"ix":5},"nm":"Transform"}],"nm":"Group 1","np":4,"cix":2,"bm":0,"ix":1,"mn":"ADBE Vector Group","hd":false},{"ty":"gr","it":[{"ind":0,"ty":"sh","ix":1,"ks":{"a":0,"k":{"i":[[-6.963,-47.533],[-64.062,-20.371],[40.387,0]],"o":[[0,0],[64.06,20.371],[-40.385,0]],"v":[[-94.698,16.491],[37.601,10.671],[0,-27.161]],"c":true},"ix":2},"nm":"Path 1","mn":"ADBE Vector Shape - Group","hd":false},{"ty":"fl","c":{"a":0,"k":[0.941176530427,0.549019607843,0.129411764706,1],"ix":4},"o":{"a":0,"k":100,"ix":5},"r":1,"bm":0,"nm":"Fill 1","mn":"ADBE Vector Graphic - Fill","hd":false},{"ty":"tr","p":{"a":0,"k":[453.544,31.292],"ix":2},"a":{"a":0,"k":[0,0],"ix":1},"s":{"a":0,"k":[100,100],"ix":3},"r":{"a":0,"k":0,"ix":6},"o":{"a":0,"k":100,"ix":7},"sk":{"a":0,"k":0,"ix":4},"sa":{"a":0,"k":0,"ix":5},"nm":"Transform"}],"nm":"Group 2","np":4,"cix":2,"bm":0,"ix":2,"mn":"ADBE Vector Group","hd":false}],"ip":0,"op":514,"st":0,"bm":0},{"ddd":0,"ind":3,"ty":4,"nm":"eyes Outlines","parent":6,"sr":1,"ks":{"o":{"a":0,"k":100,"ix":11},"r":{"a":0,"k":0,"ix":10},"p":{"a":0,"k":[176.727,-25.724,0],"ix":2},"a":{"a":0,"k":[180.215,21.011,0],"ix":1},"s":{"a":0,"k":[100,100,100],"ix":6}},"ao":0,"shapes":[{"ty":"gr","it":[{"ind":0,"ty":"sh","ix":1,"ks":{"a":1,"k":[{"i":{"x":0.833,"y":0.833},"o":{"x":0.167,"y":0.167},"t":5,"s":[{"i":[[-3.948,-8.753],[21.224,12.38],[-27.324,2.828]],"o":[[0,0],[-22.613,-13.192],[41.095,-4.251]],"v":[[48.295,9.687],[-25.682,7.243],[-20.028,-15.371]],"c":true}]},{"i":{"x":0.833,"y":0.833},"o":{"x":0.167,"y":0.167},"t":14,"s":[{"i":[[-3.948,-8.753],[25.688,0.366],[-27.324,2.828]],"o":[[0,0],[-26.177,-0.373],[41.095,-4.251]],"v":[[48.295,9.687],[-23.682,1.243],[-20.028,-15.371]],"c":true}]},{"i":{"x":0.833,"y":0.833},"o":{"x":0.167,"y":0.167},"t":18,"s":[{"i":[[-3.948,-8.753],[21.224,12.38],[-27.324,2.828]],"o":[[0,0],[-22.613,-13.192],[41.095,-4.251]],"v":[[48.295,9.687],[-25.682,7.243],[-20.028,-15.371]],"c":true}]},{"i":{"x":0.833,"y":0.833},"o":{"x":0.167,"y":0.167},"t":40,"s":[{"i":[[-3.948,-8.753],[21.224,12.38],[-27.324,2.828]],"o":[[0,0],[-22.613,-13.192],[41.095,-4.251]],"v":[[48.295,9.687],[-25.682,7.243],[-20.028,-15.371]],"c":true}]},{"i":{"x":0.833,"y":0.833},"o":{"x":0.167,"y":0.167},"t":49,"s":[{"i":[[-3.948,-8.753],[25.688,0.366],[-27.324,2.828]],"o":[[0,0],[-26.177,-0.373],[41.095,-4.251]],"v":[[48.295,9.687],[-23.682,1.243],[-20.028,-15.371]],"c":true}]},{"t":53,"s":[{"i":[[-3.948,-8.753],[21.224,12.38],[-27.324,2.828]],"o":[[0,0],[-22.613,-13.192],[41.095,-4.251]],"v":[[48.295,9.687],[-25.682,7.243],[-20.028,-15.371]],"c":true}]}],"ix":2},"nm":"Path 1","mn":"ADBE Vector Shape - Group","hd":false},{"ty":"mm","mm":4,"nm":"Merge Paths 1","mn":"ADBE Vector Filter - Merge","hd":false},{"ty":"fl","c":{"a":0,"k":[0.041123708089,0.044830879511,0.05642749188,1],"ix":4},"o":{"a":0,"k":100,"ix":5},"r":1,"bm":0,"nm":"Fill 1","mn":"ADBE Vector Graphic - Fill","hd":false},{"ty":"tr","p":{"a":0,"k":[48.545,22.149],"ix":2},"a":{"a":0,"k":[0,0],"ix":1},"s":{"a":0,"k":[100,100],"ix":3},"r":{"a":0,"k":0,"ix":6},"o":{"a":0,"k":100,"ix":7},"sk":{"a":0,"k":0,"ix":4},"sa":{"a":0,"k":0,"ix":5},"nm":"Transform"}],"nm":"Group 1","np":3,"cix":2,"bm":0,"ix":1,"mn":"ADBE Vector Group","hd":false},{"ty":"gr","it":[{"ind":0,"ty":"sh","ix":1,"ks":{"a":1,"k":[{"i":{"x":0.833,"y":0.833},"o":{"x":0.167,"y":0.167},"t":5,"s":[{"i":[[3.948,-8.752],[-23.84,10.431],[29.994,6.666]],"o":[[0,0],[15.076,-6.595],[-29.372,-6.528]],"v":[[-49.986,14.588],[34.91,8.413],[19.834,-12.316]],"c":true}]},{"i":{"x":0.833,"y":0.833},"o":{"x":0.167,"y":0.167},"t":14,"s":[{"i":[[3.948,-8.752],[-22.552,4.251],[29.994,6.666]],"o":[[0,0],[16.171,-3.048],[-29.372,-6.528]],"v":[[-49.986,14.588],[22.91,0.413],[19.834,-12.316]],"c":true}]},{"i":{"x":0.833,"y":0.833},"o":{"x":0.167,"y":0.167},"t":18,"s":[{"i":[[3.948,-8.752],[-23.84,10.431],[29.994,6.666]],"o":[[0,0],[15.076,-6.595],[-29.372,-6.528]],"v":[[-49.986,14.588],[34.91,8.413],[19.834,-12.316]],"c":true}]},{"i":{"x":0.833,"y":0.833},"o":{"x":0.167,"y":0.167},"t":40,"s":[{"i":[[3.948,-8.752],[-23.84,10.431],[29.994,6.666]],"o":[[0,0],[15.076,-6.595],[-29.372,-6.528]],"v":[[-49.986,14.588],[34.91,8.413],[19.834,-12.316]],"c":true}]},{"i":{"x":0.833,"y":0.833},"o":{"x":0.167,"y":0.167},"t":49,"s":[{"i":[[3.948,-8.752],[-22.552,4.251],[29.994,6.666]],"o":[[0,0],[16.171,-3.048],[-29.372,-6.528]],"v":[[-49.986,14.588],[22.91,0.413],[19.834,-12.316]],"c":true}]},{"t":53,"s":[{"i":[[3.948,-8.752],[-23.84,10.431],[29.994,6.666]],"o":[[0,0],[15.076,-6.595],[-29.372,-6.528]],"v":[[-49.986,14.588],[34.91,8.413],[19.834,-12.316]],"c":true}]}],"ix":2},"nm":"Path 1","mn":"ADBE Vector Shape - Group","hd":false},{"ty":"mm","mm":4,"nm":"Merge Paths 1","mn":"ADBE Vector Filter - Merge","hd":false},{"ty":"fl","c":{"a":0,"k":[0.041123708089,0.044830879511,0.05642749188,1],"ix":4},"o":{"a":0,"k":100,"ix":5},"r":1,"bm":0,"nm":"Fill 1","mn":"ADBE Vector Graphic - Fill","hd":false},{"ty":"tr","p":{"a":0,"k":[310.194,19.094],"ix":2},"a":{"a":0,"k":[0,0],"ix":1},"s":{"a":0,"k":[100,100],"ix":3},"r":{"a":0,"k":0,"ix":6},"o":{"a":0,"k":100,"ix":7},"sk":{"a":0,"k":0,"ix":4},"sa":{"a":0,"k":0,"ix":5},"nm":"Transform"}],"nm":"Group 2","np":3,"cix":2,"bm":0,"ix":2,"mn":"ADBE Vector Group","hd":false}],"ip":0,"op":514,"st":0,"bm":0},{"ddd":0,"ind":4,"ty":4,"nm":"mouth Outlines","parent":6,"sr":1,"ks":{"o":{"a":0,"k":100,"ix":11},"r":{"a":0,"k":0,"ix":10},"p":{"a":0,"k":[174.911,85.139,0],"ix":2},"a":{"a":0,"k":[41.204,21.445,0],"ix":1},"s":{"a":0,"k":[100,100,100],"ix":6}},"ao":0,"shapes":[{"ty":"gr","it":[{"ind":0,"ty":"sh","ix":1,"ks":{"a":0,"k":{"i":[[-29.444,-12.169],[22.686,7.969],[0,0]],"o":[[0,0],[-9.782,-3.436],[0,0]],"v":[[32.877,-4.029],[-10.061,8.228],[-32.877,-6.585]],"c":true},"ix":2},"nm":"Path 1","mn":"ADBE Vector Shape - Group","hd":false},{"ty":"mm","mm":4,"nm":"Merge Paths 1","mn":"ADBE Vector Filter - Merge","hd":false},{"ty":"fl","c":{"a":0,"k":[0.041123708089,0.044830879511,0.05642749188,1],"ix":4},"o":{"a":0,"k":100,"ix":5},"r":1,"bm":0,"nm":"Fill 1","mn":"ADBE Vector Graphic - Fill","hd":false},{"ty":"tr","p":{"a":0,"k":[42.918,26.443],"ix":2},"a":{"a":0,"k":[0,0],"ix":1},"s":{"a":0,"k":[100,100],"ix":3},"r":{"a":0,"k":0,"ix":6},"o":{"a":0,"k":100,"ix":7},"sk":{"a":0,"k":0,"ix":4},"sa":{"a":0,"k":0,"ix":5},"nm":"Transform"}],"nm":"Group 1","np":3,"cix":2,"bm":0,"ix":1,"mn":"ADBE Vector Group","hd":false},{"ty":"gr","it":[{"ind":0,"ty":"sh","ix":1,"ks":{"a":1,"k":[{"i":{"x":0.833,"y":0.833},"o":{"x":0.333,"y":0},"t":11,"s":[{"i":[[29.363,12.363],[-10.49,-3.764],[-9.272,-4.637],[0,0]],"o":[[0,0],[16.347,5.864],[9.273,4.635],[0,0]],"v":[[-40.954,2.318],[-2.318,-10.044],[22.408,-10.044],[40.954,5.409]],"c":true}]},{"i":{"x":0.833,"y":0.833},"o":{"x":0.167,"y":0.167},"t":29,"s":[{"i":[[25.607,19.079],[-21.529,-7.558],[-14.255,-6.058],[0,0]],"o":[[0,0],[16.386,5.753],[9.541,4.055],[0,0]],"v":[[-51.954,-4.682],[-2.318,-10.044],[27.408,-10.044],[50.454,1.409]],"c":true}]},{"i":{"x":0.667,"y":1},"o":{"x":0.167,"y":0.167},"t":51,"s":[{"i":[[25.607,19.079],[-21.529,-7.558],[-14.255,-6.058],[0,0]],"o":[[0,0],[16.386,5.753],[9.541,4.055],[0,0]],"v":[[-51.954,-4.682],[-2.318,-10.044],[27.408,-10.044],[50.454,1.409]],"c":true}]},{"t":65,"s":[{"i":[[29.363,12.363],[-10.49,-3.764],[-9.272,-4.637],[0,0]],"o":[[0,0],[16.347,5.864],[9.273,4.635],[0,0]],"v":[[-40.954,2.318],[-2.318,-10.044],[22.408,-10.044],[40.954,5.409]],"c":true}]}],"ix":2},"nm":"Path 1","mn":"ADBE Vector Shape - Group","hd":false},{"ty":"mm","mm":4,"nm":"Merge Paths 1","mn":"ADBE Vector Filter - Merge","hd":false},{"ty":"fl","c":{"a":0,"k":[0.041123708089,0.044830879511,0.05642749188,1],"ix":4},"o":{"a":0,"k":100,"ix":5},"r":1,"bm":0,"nm":"Fill 1","mn":"ADBE Vector Graphic - Fill","hd":false},{"ty":"tr","p":{"a":0,"k":[41.204,14.932],"ix":2},"a":{"a":0,"k":[0,0],"ix":1},"s":{"a":0,"k":[100,100],"ix":3},"r":{"a":0,"k":0,"ix":6},"o":{"a":0,"k":100,"ix":7},"sk":{"a":0,"k":0,"ix":4},"sa":{"a":0,"k":0,"ix":5},"nm":"Transform"}],"nm":"Group 2","np":3,"cix":2,"bm":0,"ix":2,"mn":"ADBE Vector Group","hd":false}],"ip":0,"op":514,"st":0,"bm":0},{"ddd":0,"ind":5,"ty":4,"nm":"nose Outlines","parent":6,"sr":1,"ks":{"o":{"a":0,"k":100,"ix":11},"r":{"a":0,"k":0,"ix":10},"p":{"a":0,"k":[199.301,31.626,0],"ix":2},"a":{"a":0,"k":[37.998,34.546,0],"ix":1},"s":{"a":0,"k":[100,100,100],"ix":6}},"ao":0,"shapes":[{"ty":"gr","it":[{"ind":0,"ty":"sh","ix":1,"ks":{"a":0,"k":{"i":[[38.736,0.957],[0,0]],"o":[[0,0],[0,0]],"v":[[-19.368,14.959],[-19.368,-15.917]],"c":true},"ix":2},"nm":"Path 1","mn":"ADBE Vector Shape - Group","hd":false},{"ty":"gr","it":[{"ty":"tr","p":{"a":0,"k":[0,0],"ix":2},"a":{"a":0,"k":[0,0],"ix":1},"s":{"a":0,"k":[100,100],"ix":3},"r":{"a":0,"k":0,"ix":6},"o":{"a":0,"k":100,"ix":7},"sk":{"a":0,"k":0,"ix":4},"sa":{"a":0,"k":0,"ix":5},"nm":"Transform"}],"nm":"Group 1","np":0,"cix":2,"bm":0,"ix":2,"mn":"ADBE Vector Group","hd":false},{"ty":"mm","mm":4,"nm":"Merge Paths 1","mn":"ADBE Vector Filter - Merge","hd":false},{"ty":"fl","c":{"a":0,"k":[0.945098099054,0.603921568627,0.572549019608,1],"ix":4},"o":{"a":0,"k":100,"ix":5},"r":1,"bm":0,"nm":"Fill 1","mn":"ADBE Vector Graphic - Fill","hd":false},{"ty":"tr","p":{"a":0,"k":[37.998,34.547],"ix":2},"a":{"a":0,"k":[0,0],"ix":1},"s":{"a":0,"k":[100,100],"ix":3},"r":{"a":0,"k":0,"ix":6},"o":{"a":0,"k":100,"ix":7},"sk":{"a":0,"k":0,"ix":4},"sa":{"a":0,"k":0,"ix":5},"nm":"Transform"}],"nm":"Group 2","np":4,"cix":2,"bm":0,"ix":2,"mn":"ADBE Vector Group","hd":false}],"ip":0,"op":514,"st":0,"bm":0},{"ddd":0,"ind":6,"ty":4,"nm":"cheeks Outlines","sr":1,"ks":{"o":{"a":0,"k":100,"ix":11},"r":{"a":0,"k":0,"ix":10},"p":{"a":1,"k":[{"i":{"x":0.224,"y":1},"o":{"x":0.333,"y":0},"t":0,"s":[1001.383,1227.467,0],"to":[0,3.333,0],"ti":[0,1,0]},{"i":{"x":0,"y":0.988},"o":{"x":0.692,"y":0},"t":17,"s":[1001.383,1247.467,0],"to":[0,-1,0],"ti":[0,3.333,0]},{"i":{"x":0.172,"y":0.924},"o":{"x":0.297,"y":0},"t":31,"s":[1001.383,1221.467,0],"to":[0,-3.333,0],"ti":[0,-1,0]},{"t":62,"s":[1001.383,1227.467,0]}],"ix":2},"a":{"a":0,"k":[182.447,28.49,0],"ix":1},"s":{"a":0,"k":[100,100,100],"ix":6}},"ao":0,"shapes":[{"ty":"gr","it":[{"ind":0,"ty":"sh","ix":1,"ks":{"a":0,"k":{"i":[[13.735,0],[0,0],[0,13.734],[0,0],[-13.735,0],[0,0],[0,-13.735],[0,0]],"o":[[0,0],[-13.735,0],[0,0],[0,-13.735],[0,0],[13.735,0],[0,0],[0,13.734]],"v":[[24.738,28.49],[-24.738,28.49],[-49.607,3.622],[-49.607,-3.622],[-24.738,-28.49],[24.738,-28.49],[49.607,-3.622],[49.607,3.622]],"c":true},"ix":2},"nm":"Path 1","mn":"ADBE Vector Shape - Group","hd":false},{"ty":"fl","c":{"a":0,"k":[0.945098099054,0.603921568627,0.572549019608,1],"ix":4},"o":{"a":0,"k":100,"ix":5},"r":1,"bm":0,"nm":"Fill 1","mn":"ADBE Vector Graphic - Fill","hd":false},{"ty":"tr","p":{"a":0,"k":[49.607,28.491],"ix":2},"a":{"a":0,"k":[0,0],"ix":1},"s":{"a":0,"k":[100,100],"ix":3},"r":{"a":0,"k":0,"ix":6},"o":{"a":0,"k":100,"ix":7},"sk":{"a":0,"k":0,"ix":4},"sa":{"a":0,"k":0,"ix":5},"nm":"Transform"}],"nm":"Group 1","np":4,"cix":2,"bm":0,"ix":1,"mn":"ADBE Vector Group","hd":false},{"ty":"gr","it":[{"ind":0,"ty":"sh","ix":1,"ks":{"a":0,"k":{"i":[[13.734,0],[0,0],[0,13.734],[0,0],[-13.735,0],[0,0],[0,-13.735],[0,0]],"o":[[0,0],[-13.735,0],[0,0],[0,-13.735],[0,0],[13.734,0],[0,0],[0,13.734]],"v":[[24.736,28.49],[-24.741,28.49],[-49.61,3.622],[-49.61,-3.622],[-24.741,-28.49],[24.736,-28.49],[49.605,-3.622],[49.605,3.622]],"c":true},"ix":2},"nm":"Path 1","mn":"ADBE Vector Shape - Group","hd":false},{"ty":"fl","c":{"a":0,"k":[0.945098099054,0.603921568627,0.572549019608,1],"ix":4},"o":{"a":0,"k":100,"ix":5},"r":1,"bm":0,"nm":"Fill 1","mn":"ADBE Vector Graphic - Fill","hd":false},{"ty":"tr","p":{"a":0,"k":[315.289,28.491],"ix":2},"a":{"a":0,"k":[0,0],"ix":1},"s":{"a":0,"k":[100,100],"ix":3},"r":{"a":0,"k":0,"ix":6},"o":{"a":0,"k":100,"ix":7},"sk":{"a":0,"k":0,"ix":4},"sa":{"a":0,"k":0,"ix":5},"nm":"Transform"}],"nm":"Group 2","np":4,"cix":2,"bm":0,"ix":2,"mn":"ADBE Vector Group","hd":false}],"ip":0,"op":514,"st":0,"bm":0},{"ddd":0,"ind":7,"ty":4,"nm":"tshirt","sr":1,"ks":{"o":{"a":0,"k":100,"ix":11},"r":{"a":0,"k":0,"ix":10},"p":{"a":0,"k":[951.982,1273.985,0],"ix":2},"a":{"a":0,"k":[364.635,535.912,0],"ix":1},"s":{"a":0,"k":[100,100,100],"ix":6}},"ao":0,"shapes":[{"ty":"gr","it":[{"ind":0,"ty":"sh","ix":1,"ks":{"a":0,"k":{"i":[[0,0],[-40.189,81.099],[-8.394,-12.481],[-46.322,1.362],[-21.512,-2.165],[-31.12,-30.005],[0,0],[202.664,-3.897]],"o":[[0,0],[26.291,-53.055],[3.21,4.773],[59.049,-1.737],[36.206,3.642],[86.114,83.029],[0,0],[-202.664,3.898]],"v":[[-231.354,116.219],[-128.824,-107.3],[-4.619,-161.72],[11.695,-129.932],[54.825,-163.357],[168.107,-124.196],[355.354,71.153],[24.076,168.587]],"c":true},"ix":2},"nm":"Path 1","mn":"ADBE Vector Shape - Group","hd":false},{"ty":"gr","it":[{"ty":"tr","p":{"a":0,"k":[0,0],"ix":2},"a":{"a":0,"k":[0,0],"ix":1},"s":{"a":0,"k":[100,100],"ix":3},"r":{"a":0,"k":0,"ix":6},"o":{"a":0,"k":100,"ix":7},"sk":{"a":0,"k":0,"ix":4},"sa":{"a":0,"k":0,"ix":5},"nm":"Transform"}],"nm":"Group 1","np":0,"cix":2,"bm":0,"ix":2,"mn":"ADBE Vector Group","hd":false},{"ty":"mm","mm":4,"nm":"Merge Paths 1","mn":"ADBE Vector Filter - Merge","hd":false},{"ty":"fl","c":{"a":0,"k":[0,0,0,1],"ix":4},"o":{"a":0,"k":100,"ix":5},"r":1,"bm":0,"nm":"Fill 1","mn":"ADBE Vector Graphic - Fill","hd":false},{"ty":"tr","p":{"a":0,"k":[373.666,884.128],"ix":2},"a":{"a":0,"k":[0,0],"ix":1},"s":{"a":0,"k":[100,100],"ix":3},"r":{"a":0,"k":0,"ix":6},"o":{"a":0,"k":100,"ix":7},"sk":{"a":0,"k":0,"ix":4},"sa":{"a":0,"k":0,"ix":5},"nm":"Transform"}],"nm":"Group 1","np":4,"cix":2,"bm":0,"ix":1,"mn":"ADBE Vector Group","hd":false}],"ip":0,"op":514,"st":0,"bm":0},{"ddd":0,"ind":8,"ty":4,"nm":"skin","sr":1,"ks":{"o":{"a":0,"k":100,"ix":11},"r":{"a":0,"k":0,"ix":10},"p":{"a":0,"k":[951.982,1273.985,0],"ix":2},"a":{"a":0,"k":[364.635,535.912,0],"ix":1},"s":{"a":0,"k":[100,100,100],"ix":6}},"ao":0,"shapes":[{"ty":"gr","it":[{"ind":0,"ty":"sh","ix":1,"ks":{"a":0,"k":{"i":[[0,260.473],[-137.537,0],[-3.813,-137.484],[170.448,-6.7]],"o":[[0,-137.537],[137.537,0],[7.224,260.474],[-193.716,7.615]],"v":[[-232.919,-48.633],[10.548,-243.395],[225.695,-32.897],[-5.452,299.78]],"c":true},"ix":2},"nm":"Path 1","mn":"ADBE Vector Shape - Group","hd":false},{"ty":"st","c":{"a":0,"k":[0,0,0,1],"ix":3},"o":{"a":0,"k":100,"ix":4},"w":{"a":0,"k":10,"ix":5},"lc":1,"lj":1,"ml":10,"bm":0,"nm":"Stroke 1","mn":"ADBE Vector Graphic - Stroke","hd":false},{"ty":"tr","p":{"a":0,"k":[409.012,350.618],"ix":2},"a":{"a":0,"k":[0,0],"ix":1},"s":{"a":0,"k":[100,100],"ix":3},"r":{"a":0,"k":0,"ix":6},"o":{"a":0,"k":100,"ix":7},"sk":{"a":0,"k":0,"ix":4},"sa":{"a":0,"k":0,"ix":5},"nm":"Transform"}],"nm":"Group 2","np":2,"cix":2,"bm":0,"ix":1,"mn":"ADBE Vector Group","hd":false},{"ty":"gr","it":[{"ind":0,"ty":"sh","ix":1,"ks":{"a":0,"k":{"i":[[0,260.473],[-137.537,0],[-3.813,-137.484],[170.448,-6.7]],"o":[[0,-137.537],[137.537,0],[7.224,260.474],[-193.716,7.615]],"v":[[-232.919,-48.633],[-5.452,-259.395],[225.695,-32.897],[-5.452,299.78]],"c":true},"ix":2},"nm":"Path 1","mn":"ADBE Vector Shape - Group","hd":false},{"ty":"gr","it":[{"ty":"tr","p":{"a":0,"k":[0,0],"ix":2},"a":{"a":0,"k":[0,0],"ix":1},"s":{"a":0,"k":[100,100],"ix":3},"r":{"a":0,"k":0,"ix":6},"o":{"a":0,"k":100,"ix":7},"sk":{"a":0,"k":0,"ix":4},"sa":{"a":0,"k":0,"ix":5},"nm":"Transform"}],"nm":"Group 1","np":0,"cix":2,"bm":0,"ix":2,"mn":"ADBE Vector Group","hd":false},{"ty":"mm","mm":4,"nm":"Merge Paths 1","mn":"ADBE Vector Filter - Merge","hd":false},{"ty":"fl","c":{"a":0,"k":[0.992156922583,0.878431432387,0.796078491211,1],"ix":4},"o":{"a":0,"k":100,"ix":5},"r":1,"bm":0,"nm":"Fill 1","mn":"ADBE Vector Graphic - Fill","hd":false},{"ty":"tr","p":{"a":0,"k":[409.012,350.618],"ix":2},"a":{"a":0,"k":[0,0],"ix":1},"s":{"a":0,"k":[100,100],"ix":3},"r":{"a":0,"k":0,"ix":6},"o":{"a":0,"k":100,"ix":7},"sk":{"a":0,"k":0,"ix":4},"sa":{"a":0,"k":0,"ix":5},"nm":"Transform"}],"nm":"Group 3","np":4,"cix":2,"bm":0,"ix":2,"mn":"ADBE Vector Group","hd":false},{"ty":"gr","it":[{"ind":0,"ty":"sh","ix":1,"ks":{"a":0,"k":{"i":[[0,-34.978],[34.978,0],[0,34.979],[-34.979,0]],"o":[[0,34.979],[-34.979,0],[0,-34.978],[34.978,0]],"v":[[63.334,0],[0,63.334],[-63.334,0],[0,-63.334]],"c":true},"ix":2},"nm":"Path 1","mn":"ADBE Vector Shape - Group","hd":false},{"ty":"st","c":{"a":0,"k":[0.999999940162,0.999999940162,1,1],"ix":3},"o":{"a":0,"k":100,"ix":4},"w":{"a":0,"k":10,"ix":5},"lc":1,"lj":1,"ml":10,"bm":0,"nm":"Stroke 1","mn":"ADBE Vector Graphic - Stroke","hd":false},{"ty":"tr","p":{"a":0,"k":[596.483,552.728],"ix":2},"a":{"a":0,"k":[0,0],"ix":1},"s":{"a":0,"k":[100,100],"ix":3},"r":{"a":0,"k":0,"ix":6},"o":{"a":0,"k":100,"ix":7},"sk":{"a":0,"k":0,"ix":4},"sa":{"a":0,"k":0,"ix":5},"nm":"Transform"}],"nm":"Group 4","np":2,"cix":2,"bm":0,"ix":3,"mn":"ADBE Vector Group","hd":false},{"ty":"gr","it":[{"ind":0,"ty":"sh","ix":1,"ks":{"a":0,"k":{"i":[[0,-34.978],[34.979,0],[0,34.979],[-34.978,0]],"o":[[0,34.979],[-34.978,0],[0,-34.978],[34.979,0]],"v":[[63.334,0],[0,63.334],[-63.334,0],[0,-63.334]],"c":true},"ix":2},"nm":"Path 1","mn":"ADBE Vector Shape - Group","hd":false},{"ty":"st","c":{"a":0,"k":[0.999999940162,0.999999940162,1,1],"ix":3},"o":{"a":0,"k":100,"ix":4},"w":{"a":0,"k":10,"ix":5},"lc":1,"lj":1,"ml":10,"bm":0,"nm":"Stroke 1","mn":"ADBE Vector Graphic - Stroke","hd":false},{"ty":"tr","p":{"a":0,"k":[217.862,552.728],"ix":2},"a":{"a":0,"k":[0,0],"ix":1},"s":{"a":0,"k":[100,100],"ix":3},"r":{"a":0,"k":0,"ix":6},"o":{"a":0,"k":100,"ix":7},"sk":{"a":0,"k":0,"ix":4},"sa":{"a":0,"k":0,"ix":5},"nm":"Transform"}],"nm":"Group 5","np":2,"cix":2,"bm":0,"ix":4,"mn":"ADBE Vector Group","hd":false},{"ty":"gr","it":[{"ind":0,"ty":"sh","ix":1,"ks":{"a":0,"k":{"i":[[0,0],[0,0],[38.209,-20.841],[0,0],[0,0],[0,0],[29.525,20.841],[0,0],[0,0],[0,0]],"o":[[0,0],[0,0],[-38.208,20.84],[0,0],[0,0],[0,0],[-29.524,-20.842],[0,0],[0,0],[0,0]],"v":[[29.842,-206.269],[29.842,-93.852],[-63.364,-35.502],[-128.983,185.012],[55.575,206.27],[296.983,159.377],[195.41,-18.555],[88.285,-81.559],[88.285,-206.269],[46.388,-206.269]],"c":true},"ix":2},"nm":"Path 1","mn":"ADBE Vector Shape - Group","hd":false},{"ty":"st","c":{"a":0,"k":[0,0,0,1],"ix":3},"o":{"a":0,"k":100,"ix":4},"w":{"a":0,"k":10,"ix":5},"lc":1,"lj":1,"ml":10,"bm":0,"nm":"Stroke 1","mn":"ADBE Vector Graphic - Stroke","hd":false},{"ty":"tr","p":{"a":0,"k":[340.205,822.331],"ix":2},"a":{"a":0,"k":[0,0],"ix":1},"s":{"a":0,"k":[100,100],"ix":3},"r":{"a":0,"k":0,"ix":6},"o":{"a":0,"k":100,"ix":7},"sk":{"a":0,"k":0,"ix":4},"sa":{"a":0,"k":0,"ix":5},"nm":"Transform"}],"nm":"Group 6","np":2,"cix":2,"bm":0,"ix":5,"mn":"ADBE Vector Group","hd":false},{"ty":"gr","it":[{"ind":0,"ty":"sh","ix":1,"ks":{"a":0,"k":{"i":[[0,0],[0,0],[38.209,-20.841],[0,0],[0,0],[0,0],[29.525,20.841],[0,0],[0,0],[0,0]],"o":[[0,0],[0,0],[-38.208,20.84],[0,0],[0,0],[0,0],[-29.524,-20.842],[0,0],[0,0],[0,0]],"v":[[29.842,-206.269],[29.842,-93.852],[-65.364,-27.502],[-128.983,189.012],[55.575,206.27],[292.983,155.377],[193.41,-24.555],[88.285,-81.559],[88.285,-206.269],[46.388,-206.269]],"c":true},"ix":2},"nm":"Path 1","mn":"ADBE Vector Shape - Group","hd":false},{"ty":"gr","it":[{"ty":"tr","p":{"a":0,"k":[0,0],"ix":2},"a":{"a":0,"k":[0,0],"ix":1},"s":{"a":0,"k":[100,100],"ix":3},"r":{"a":0,"k":0,"ix":6},"o":{"a":0,"k":100,"ix":7},"sk":{"a":0,"k":0,"ix":4},"sa":{"a":0,"k":0,"ix":5},"nm":"Transform"}],"nm":"Group 1","np":0,"cix":2,"bm":0,"ix":2,"mn":"ADBE Vector Group","hd":false},{"ty":"mm","mm":4,"nm":"Merge Paths 1","mn":"ADBE Vector Filter - Merge","hd":false},{"ty":"fl","c":{"a":0,"k":[0.992156922583,0.878431432387,0.796078491211,1],"ix":4},"o":{"a":0,"k":100,"ix":5},"r":1,"bm":0,"nm":"Fill 1","mn":"ADBE Vector Graphic - Fill","hd":false},{"ty":"tr","p":{"a":0,"k":[340.205,822.331],"ix":2},"a":{"a":0,"k":[0,0],"ix":1},"s":{"a":0,"k":[100,100],"ix":3},"r":{"a":0,"k":0,"ix":6},"o":{"a":0,"k":100,"ix":7},"sk":{"a":0,"k":0,"ix":4},"sa":{"a":0,"k":0,"ix":5},"nm":"Transform"}],"nm":"Group 7","np":4,"cix":2,"bm":0,"ix":6,"mn":"ADBE Vector Group","hd":false}],"ip":0,"op":514,"st":0,"bm":0},{"ddd":0,"ind":9,"ty":4,"nm":"hair","sr":1,"ks":{"o":{"a":0,"k":100,"ix":11},"r":{"a":0,"k":0,"ix":10},"p":{"a":0,"k":[951.982,1273.985,0],"ix":2},"a":{"a":0,"k":[364.635,535.912,0],"ix":1},"s":{"a":0,"k":[100,100,100],"ix":6}},"ao":0,"shapes":[{"ty":"gr","it":[{"ind":0,"ty":"sh","ix":1,"ks":{"a":1,"k":[{"i":{"x":0.833,"y":0.833},"o":{"x":0.167,"y":0.167},"t":7,"s":[{"i":[[103.744,-72.62],[37.566,-82.8],[0,0],[-188.488,4.914],[0,0],[24.631,107.759]],"o":[[0,0],[-69.976,154.232],[0,0],[157.322,-4.101],[0,0],[-42.219,-184.709]],"v":[[-64.047,-232.434],[-250.172,-106.973],[-320.892,239.982],[-9.366,300.141],[314.618,271.531],[296.262,-1.12]],"c":true}]},{"i":{"x":0.833,"y":0.833},"o":{"x":0.167,"y":0.167},"t":29,"s":[{"i":[[103.744,-72.62],[37.566,-82.8],[0,0],[-188.488,4.914],[0,0],[24.631,107.759]],"o":[[0,0],[-69.976,154.232],[0,0],[157.322,-4.101],[0,0],[-42.219,-184.709]],"v":[[-64.047,-258.435],[-250.172,-132.973],[-320.892,213.982],[-9.366,274.141],[314.618,245.531],[296.262,-27.12]],"c":true}]},{"t":57,"s":[{"i":[[103.744,-72.62],[37.566,-82.8],[0,0],[-188.488,4.914],[0,0],[24.631,107.759]],"o":[[0,0],[-69.976,154.232],[0,0],[157.322,-4.101],[0,0],[-42.219,-184.709]],"v":[[-64.047,-232.434],[-250.172,-106.973],[-320.892,239.982],[-9.366,300.141],[314.618,271.531],[296.262,-1.12]],"c":true}]}],"ix":2},"nm":"Path 1","mn":"ADBE Vector Shape - Group","hd":false},{"ty":"mm","mm":4,"nm":"Merge Paths 1","mn":"ADBE Vector Filter - Merge","hd":false},{"ty":"fl","c":{"a":0,"k":[0.941176530427,0.549019607843,0.129411764706,1],"ix":4},"o":{"a":0,"k":100,"ix":5},"r":1,"bm":0,"nm":"Fill 1","mn":"ADBE Vector Graphic - Fill","hd":false},{"ty":"tr","p":{"a":0,"k":[395.959,315.921],"ix":2},"a":{"a":0,"k":[0,0],"ix":1},"s":{"a":0,"k":[100,100],"ix":3},"r":{"a":0,"k":0,"ix":6},"o":{"a":0,"k":100,"ix":7},"sk":{"a":0,"k":0,"ix":4},"sa":{"a":0,"k":0,"ix":5},"nm":"Transform"}],"nm":"Group 8","np":3,"cix":2,"bm":0,"ix":1,"mn":"ADBE Vector Group","hd":false}],"ip":0,"op":514,"st":0,"bm":0},{"ddd":0,"ind":10,"ty":4,"nm":"circle","sr":1,"ks":{"o":{"a":0,"k":100,"ix":11},"r":{"a":0,"k":0,"ix":10},"p":{"a":0,"k":[960,964.188,0],"ix":2},"a":{"a":0,"k":[824.122,846.804,0],"ix":1},"s":{"a":0,"k":[100,100,100],"ix":6}},"ao":0,"shapes":[{"ty":"gr","it":[{"ind":0,"ty":"sh","ix":1,"ks":{"a":0,"k":{"i":[[0,-455.012],[455.012,0],[0,455.012],[-455.012,0]],"o":[[0,455.012],[-455.012,0],[0,-455.012],[455.012,0]],"v":[[823.872,0],[0,823.872],[-823.872,0],[0,-823.872]],"c":true},"ix":2},"nm":"Path 1","mn":"ADBE Vector Shape - Group","hd":false},{"ty":"fl","c":{"a":0,"k":[0.792156862745,0.854901960784,0.866666666667,1],"ix":4},"o":{"a":0,"k":100,"ix":5},"r":1,"bm":0,"nm":"Fill 1","mn":"ADBE Vector Graphic - Fill","hd":false},{"ty":"tr","p":{"a":0,"k":[824.122,824.122],"ix":2},"a":{"a":0,"k":[0,0],"ix":1},"s":{"a":0,"k":[100,100],"ix":3},"r":{"a":0,"k":0,"ix":6},"o":{"a":0,"k":100,"ix":7},"sk":{"a":0,"k":0,"ix":4},"sa":{"a":0,"k":0,"ix":5},"nm":"Transform"}],"nm":"Group 8","np":2,"cix":2,"bm":0,"ix":1,"mn":"ADBE Vector Group","hd":false}],"ip":0,"op":514,"st":0,"bm":0}],"markers":[]}